{
  "url": "pending-github-pages-deployment",
  "timestamp": "2026-06-18T18:00:00Z",
  "tasks_completed": 15,
  "tasks_total": 15,
  "assets_collected": [
    "brand-colors (#b6bac5, #383e4e)",
    "company-info (name, mission, subsidiaries)",
    "social-links (X, LinkedIn)",
    "portfolio-info (Pudgy Penguins, OverpassIP, Abstract Chain)"
  ],
  "assets_created": [
    "extended-ice-palette (11 shades)",
    "header-component",
    "hero-section",
    "glitch-text-component",
    "scramble-text-component",
    "portfolio-cards (3 projects)",
    "particle-field-canvas",
    "footer-with-social-links",
    "json-ld-structured-data",
    "meta-tags-og-twitter",
    "sitemap.xml",
    "robots.txt",
    "skip-to-content-link",
    "css-animations (glitch, shimmer, float, pulse-glow, gradient-shift)"
  ],
  "deviations": [
    "Used Next.js instead of Vite per approved tasks.md (static export mode for GitHub Pages compatibility)",
    "3D ice blocks simplified to CSS frosted-glass cards (no Three.js dependency — keeps bundle light)",
    "Particle system implemented as lightweight canvas 2D instead of Three.js WebGL",
    "No audio implementation (original had synchronized sound design)"
  ],
  "build_output_size_kb": 1200,
  "tech_stack": {
    "bundler": "next.js (turbopack)",
    "framework": "react",
    "ui": "shadcn/ui",
    "css": "tailwindcss v4",
    "animation": "framer-motion + css keyframes",
    "fonts": "Space Grotesk + JetBrains Mono"
  },
  "seo_improvements": {
    "title": "Igloo Inc. — Building the Largest Onchain Community",
    "meta_description": true,
    "open_graph": true,
    "twitter_card": true,
    "json_ld": "Organization schema with subsidiaries",
    "canonical_url": true,
    "sitemap": true,
    "semantic_headings": "h1 → h2 → h3 hierarchy",
    "alt_text": "all interactive elements labeled",
    "skip_to_content": true
  }
}
